{
  "addresses": {
    "DonorConsent": "0x5FbDB2315678afecb367f032d93F642f64180aa3",
    "OrganLifecycle": "0xe7f1725E7734CE288F8367e1Bb143E90bb3F0512",
    "LifeToken": "0x9fE46736679d2D9a65F0992F2272dE9f3c7fa6e0",
    "ChainOfCustody": "0xCf7Ed3AccA5a467e9e704C703E8D87F634fB0Fc9"
  },
  "abis": {
    "DonorConsent": "[{\"type\":\"event\",\"anonymous\":false,\"name\":\"ConsentUpdated\",\"inputs\":[{\"type\":\"address\",\"name\":\"donor\",\"indexed\":true},{\"type\":\"bool\",\"name\":\"consent\",\"indexed\":false}]},{\"type\":\"event\",\"anonymous\":false,\"name\":\"DonorRegistered\",\"inputs\":[{\"type\":\"address\",\"name\":\"donor\",\"indexed\":true},{\"type\":\"string\",\"name\":\"name\",\"indexed\":false},{\"type\":\"uint256\",\"name\":\"timestamp\",\"indexed\":false}]},{\"type\":\"event\",\"anonymous\":false,\"name\":\"HealthCardUpdated\",\"inputs\":[{\"type\":\"address\",\"name\":\"donor\",\"indexed\":true},{\"type\":\"string\",\"name\":\"newCID\",\"indexed\":false}]},{\"type\":\"function\",\"name\":\"donorList\",\"constant\":true,\"stateMutability\":\"view\",\"payable\":false,\"inputs\":[{\"type\":\"uint256\",\"name\":\"\"}],\"outputs\":[{\"type\":\"address\",\"name\":\"\"}]},{\"type\":\"function\",\"name\":\"donors\",\"constant\":true,\"stateMutability\":\"view\",\"payable\":false,\"inputs\":[{\"type\":\"address\",\"name\":\"\"}],\"outputs\":[{\"type\":\"address\",\"name\":\"donorAddress\"},{\"type\":\"string\",\"name\":\"name\"},{\"type\":\"uint256\",\"name\":\"age\"},{\"type\":\"string\",\"name\":\"bloodType\"},{\"type\":\"bool\",\"name\":\"isActive\"},{\"type\":\"uint256\",\"name\":\"registrationTime\"},{\"type\":\"string\",\"name\":\"healthCardCID\"},{\"type\":\"bool\",\"name\":\"familyConsent\"}]},{\"type\":\"function\",\"name\":\"getAllDonors\",\"constant\":true,\"stateMutability\":\"view\",\"payable\":false,\"inputs\":[],\"outputs\":[{\"type\":\"address[]\",\"name\":\"\"}]},{\"type\":\"function\",\"name\":\"getDonor\",\"constant\":true,\"stateMutability\":\"view\",\"payable\":false,\"inputs\":[{\"type\":\"address\",\"name\":\"_donorAddress\"}],\"outputs\":[{\"type\":\"tuple\",\"name\":\"\",\"components\":[{\"type\":\"address\",\"name\":\"donorAddress\"},{\"type\":\"string\",\"name\":\"name\"},{\"type\":\"uint256\",\"name\":\"age\"},{\"type\":\"string\",\"name\":\"bloodType\"},{\"type\":\"string[]\",\"name\":\"organTypes\"},{\"type\":\"bool\",\"name\":\"isActive\"},{\"type\":\"uint256\",\"name\":\"registrationTime\"},{\"type\":\"string\",\"name\":\"healthCardCID\"},{\"type\":\"bool\",\"name\":\"familyConsent\"}]}]},{\"type\":\"function\",\"name\":\"getDonorCount\",\"constant\":true,\"stateMutability\":\"view\",\"payable\":false,\"inputs\":[],\"outputs\":[{\"type\":\"uint256\",\"name\":\"\"}]},{\"type\":\"function\",\"name\":\"isRegistered\",\"constant\":true,\"stateMutability\":\"view\",\"payable\":false,\"inputs\":[{\"type\":\"address\",\"name\":\"\"}],\"outputs\":[{\"type\":\"bool\",\"name\":\"\"}]},{\"type\":\"function\",\"name\":\"registerDonor\",\"constant\":false,\"payable\":false,\"inputs\":[{\"type\":\"string\",\"name\":\"_name\"},{\"type\":\"uint256\",\"name\":\"_age\"},{\"type\":\"string\",\"name\":\"_bloodType\"},{\"type\":\"string[]\",\"name\":\"_organTypes\"},{\"type\":\"string\",\"name\":\"_healthCardCID\"}],\"outputs\":[]},{\"type\":\"function\",\"name\":\"updateConsent\",\"constant\":false,\"payable\":false,\"inputs\":[{\"type\":\"bool\",\"name\":\"_consent\"}],\"outputs\":[]},{\"type\":\"function\",\"name\":\"updateHealthCard\",\"constant\":false,\"payable\":false,\"inputs\":[{\"type\":\"string\",\"name\":\"_newCID\"}],\"outputs\":[]}]",
    "OrganLifecycle": "[{\"type\":\"event\",\"anonymous\":false,\"name\":\"OrganMatched\",\"inputs\":[{\"type\":\"uint256\",\"name\":\"organId\",\"indexed\":true},{\"type\":\"address\",\"name\":\"recipient\",\"indexed\":true},{\"type\":\"uint256\",\"name\":\"matchScore\",\"indexed\":false}]},{\"type\":\"event\",\"anonymous\":false,\"name\":\"OrganRegistered\",\"inputs\":[{\"type\":\"uint256\",\"name\":\"organId\",\"indexed\":true},{\"type\":\"address\",\"name\":\"donor\",\"indexed\":true},{\"type\":\"string\",\"name\":\"organType\",\"indexed\":false}]},{\"type\":\"event\",\"anonymous\":false,\"name\":\"OrganStatusUpdated\",\"inputs\":[{\"type\":\"uint256\",\"name\":\"organId\",\"indexed\":true},{\"type\":\"uint8\",\"name\":\"newStatus\",\"indexed\":false}]},{\"type\":\"event\",\"anonymous\":false,\"name\":\"RecipientRegistered\",\"inputs\":[{\"type\":\"address\",\"name\":\"recipient\",\"indexed\":true},{\"type\":\"string\",\"name\":\"name\",\"indexed\":false},{\"type\":\"string\",\"name\":\"requiredOrgan\",\"indexed\":false}]},{\"type\":\"event\",\"anonymous\":false,\"name\":\"TransportStarted\",\"inputs\":[{\"type\":\"uint256\",\"name\":\"organId\",\"indexed\":true},{\"type\":\"string\",\"name\":\"transportDocCID\",\"indexed\":false}]},{\"type\":\"function\",\"name\":\"completeTransplant\",\"constant\":false,\"payable\":false,\"inputs\":[{\"type\":\"uint256\",\"name\":\"_organId\"}],\"outputs\":[]},{\"type\":\"function\",\"name\":\"getAllRecipients\",\"constant\":true,\"stateMutability\":\"view\",\"payable\":false,\"inputs\":[],\"outputs\":[{\"type\":\"address[]\",\"name\":\"\"}]},{\"type\":\"function\",\"name\":\"getOrgan\",\"constant\":true,\"stateMutability\":\"view\",\"payable\":false,\"inputs\":[{\"type\":\"uint256\",\"name\":\"_organId\"}],\"outputs\":[{\"type\":\"tuple\",\"name\":\"\",\"components\":[{\"type\":\"uint256\",\"name\":\"organId\"},{\"type\":\"address\",\"name\":\"donor\"},{\"type\":\"string\",\"name\":\"organType\"},{\"type\":\"uint256\",\"name\":\"harvestTime\"},{\"type\":\"uint256\",\"name\":\"expiryTime\"},{\"type\":\"address\",\"name\":\"matchedRecipient\"},{\"type\":\"uint8\",\"name\":\"status\"},{\"type\":\"string\",\"name\":\"transportDocCID\"},{\"type\":\"uint256\",\"name\":\"aiMatchScore\"}]}]},{\"type\":\"function\",\"name\":\"getRecipient\",\"constant\":true,\"stateMutability\":\"view\",\"payable\":false,\"inputs\":[{\"type\":\"address\",\"name\":\"_recipient\"}],\"outputs\":[{\"type\":\"tuple\",\"name\":\"\",\"components\":[{\"type\":\"address\",\"name\":\"recipientAddress\"},{\"type\":\"string\",\"name\":\"name\"},{\"type\":\"string\",\"name\":\"bloodType\"},{\"type\":\"string\",\"name\":\"requiredOrgan\"},{\"type\":\"uint256\",\"name\":\"urgencyScore\"},{\"type\":\"uint256\",\"name\":\"registrationTime\"},{\"type\":\"bool\",\"name\":\"isActive\"}]}]},{\"type\":\"function\",\"name\":\"isRecipientRegistered\",\"constant\":true,\"stateMutability\":\"view\",\"payable\":false,\"inputs\":[{\"type\":\"address\",\"name\":\"\"}],\"outputs\":[{\"type\":\"bool\",\"name\":\"\"}]},{\"type\":\"function\",\"name\":\"markExpired\",\"constant\":false,\"payable\":false,\"inputs\":[{\"type\":\"uint256\",\"name\":\"_organId\"}],\"outputs\":[]},{\"type\":\"function\",\"name\":\"matchOrgan\",\"constant\":false,\"payable\":false,\"inputs\":[{\"type\":\"uint256\",\"name\":\"_organId\"},{\"type\":\"address\",\"name\":\"_recipient\"},{\"type\":\"uint256\",\"name\":\"_matchScore\"}],\"outputs\":[]},{\"type\":\"function\",\"name\":\"organCounter\",\"constant\":true,\"stateMutability\":\"view\",\"payable\":false,\"inputs\":[],\"outputs\":[{\"type\":\"uint256\",\"name\":\"\"}]},{\"type\":\"function\",\"name\":\"organs\",\"constant\":true,\"stateMutability\":\"view\",\"payable\":false,\"inputs\":[{\"type\":\"uint256\",\"name\":\"\"}],\"outputs\":[{\"type\":\"uint256\",\"name\":\"organId\"},{\"type\":\"address\",\"name\":\"donor\"},{\"type\":\"string\",\"name\":\"organType\"},{\"type\":\"uint256\",\"name\":\"harvestTime\"},{\"type\":\"uint256\",\"name\":\"expiryTime\"},{\"type\":\"address\",\"name\":\"matchedRecipient\"},{\"type\":\"uint8\",\"name\":\"status\"},{\"type\":\"string\",\"name\":\"transportDocCID\"},{\"type\":\"uint256\",\"name\":\"aiMatchScore\"}]},{\"type\":\"function\",\"name\":\"recipientList\",\"constant\":true,\"stateMutability\":\"view\",\"payable\":false,\"inputs\":[{\"type\":\"uint256\",\"name\":\"\"}],\"outputs\":[{\"type\":\"address\",\"name\":\"\"}]},{\"type\":\"function\",\"name\":\"recipients\",\"constant\":true,\"stateMutability\":\"view\",\"payable\":false,\"inputs\":[{\"type\":\"address\",\"name\":\"\"}],\"outputs\":[{\"type\":\"address\",\"name\":\"recipientAddress\"},{\"type\":\"string\",\"name\":\"name\"},{\"type\":\"string\",\"name\":\"bloodType\"},{\"type\":\"string\",\"name\":\"requiredOrgan\"},{\"type\":\"uint256\",\"name\":\"urgencyScore\"},{\"type\":\"uint256\",\"name\":\"registrationTime\"},{\"type\":\"bool\",\"name\":\"isActive\"}]},{\"type\":\"function\",\"name\":\"registerOrgan\",\"constant\":false,\"payable\":false,\"inputs\":[{\"type\":\"address\",\"name\":\"_donor\"},{\"type\":\"string\",\"name\":\"_organType\"},{\"type\":\"uint256\",\"name\":\"_expiryHours\"}],\"outputs\":[{\"type\":\"uint256\",\"name\":\"\"}]},{\"type\":\"function\",\"name\":\"registerRecipient\",\"constant\":false,\"payable\":false,\"inputs\":[{\"type\":\"string\",\"name\":\"_name\"},{\"type\":\"string\",\"name\":\"_bloodType\"},{\"type\":\"string\",\"name\":\"_requiredOrgan\"},{\"type\":\"uint256\",\"name\":\"_urgencyScore\"}],\"outputs\":[]},{\"type\":\"function\",\"name\":\"startTransport\",\"constant\":false,\"payable\":false,\"inputs\":[{\"type\":\"uint256\",\"name\":\"_organId\"},{\"type\":\"string\",\"name\":\"_transportDocCID\"}],\"outputs\":[]}]",
    "LifeToken": "[{\"type\":\"constructor\",\"stateMutability\":\"undefined\",\"payable\":false,\"inputs\":[]},{\"type\":\"error\",\"name\":\"ERC20InsufficientAllowance\",\"inputs\":[{\"type\":\"address\",\"name\":\"spender\"},{\"type\":\"uint256\",\"name\":\"allowance\"},{\"type\":\"uint256\",\"name\":\"needed\"}]},{\"type\":\"error\",\"name\":\"ERC20InsufficientBalance\",\"inputs\":[{\"type\":\"address\",\"name\":\"sender\"},{\"type\":\"uint256\",\"name\":\"balance\"},{\"type\":\"uint256\",\"name\":\"needed\"}]},{\"type\":\"error\",\"name\":\"ERC20InvalidApprover\",\"inputs\":[{\"type\":\"address\",\"name\":\"approver\"}]},{\"type\":\"error\",\"name\":\"ERC20InvalidReceiver\",\"inputs\":[{\"type\":\"address\",\"name\":\"receiver\"}]},{\"type\":\"error\",\"name\":\"ERC20InvalidSender\",\"inputs\":[{\"type\":\"address\",\"name\":\"sender\"}]},{\"type\":\"error\",\"name\":\"ERC20InvalidSpender\",\"inputs\":[{\"type\":\"address\",\"name\":\"spender\"}]},{\"type\":\"error\",\"name\":\"OwnableInvalidOwner\",\"inputs\":[{\"type\":\"address\",\"name\":\"owner\"}]},{\"type\":\"error\",\"name\":\"OwnableUnauthorizedAccount\",\"inputs\":[{\"type\":\"address\",\"name\":\"account\"}]},{\"type\":\"event\",\"anonymous\":false,\"name\":\"Approval\",\"inputs\":[{\"type\":\"address\",\"name\":\"owner\",\"indexed\":true},{\"type\":\"address\",\"name\":\"spender\",\"indexed\":true},{\"type\":\"uint256\",\"name\":\"value\",\"indexed\":false}]},{\"type\":\"event\",\"anonymous\":false,\"name\":\"MinterAuthorized\",\"inputs\":[{\"type\":\"address\",\"name\":\"minter\",\"indexed\":true}]},{\"type\":\"event\",\"anonymous\":false,\"name\":\"MinterRevoked\",\"inputs\":[{\"type\":\"address\",\"name\":\"minter\",\"indexed\":true}]},{\"type\":\"event\",\"anonymous\":false,\"name\":\"OwnershipTransferred\",\"inputs\":[{\"type\":\"address\",\"name\":\"previousOwner\",\"indexed\":true},{\"type\":\"address\",\"name\":\"newOwner\",\"indexed\":true}]},{\"type\":\"event\",\"anonymous\":false,\"name\":\"RewardMinted\",\"inputs\":[{\"type\":\"address\",\"name\":\"recipient\",\"indexed\":true},{\"type\":\"uint256\",\"name\":\"amount\",\"indexed\":false},{\"type\":\"string\",\"name\":\"reason\",\"indexed\":false}]},{\"type\":\"event\",\"anonymous\":false,\"name\":\"Transfer\",\"inputs\":[{\"type\":\"address\",\"name\":\"from\",\"indexed\":true},{\"type\":\"address\",\"name\":\"to\",\"indexed\":true},{\"type\":\"uint256\",\"name\":\"value\",\"indexed\":false}]},{\"type\":\"function\",\"name\":\"ANNUAL_REWARD\",\"constant\":true,\"stateMutability\":\"view\",\"payable\":false,\"inputs\":[],\"outputs\":[{\"type\":\"uint256\",\"name\":\"\"}]},{\"type\":\"function\",\"name\":\"DONATION_REWARD\",\"constant\":true,\"stateMutability\":\"view\",\"payable\":false,\"inputs\":[],\"outputs\":[{\"type\":\"uint256\",\"name\":\"\"}]},{\"type\":\"function\",\"name\":\"REGISTRATION_REWARD\",\"constant\":true,\"stateMutability\":\"view\",\"payable\":false,\"inputs\":[],\"outputs\":[{\"type\":\"uint256\",\"name\":\"\"}]},{\"type\":\"function\",\"name\":\"allowance\",\"constant\":true,\"stateMutability\":\"view\",\"payable\":false,\"inputs\":[{\"type\":\"address\",\"name\":\"owner\"},{\"type\":\"address\",\"name\":\"spender\"}],\"outputs\":[{\"type\":\"uint256\",\"name\":\"\"}]},{\"type\":\"function\",\"name\":\"approve\",\"constant\":false,\"payable\":false,\"inputs\":[{\"type\":\"address\",\"name\":\"spender\"},{\"type\":\"uint256\",\"name\":\"value\"}],\"outputs\":[{\"type\":\"bool\",\"name\":\"\"}]},{\"type\":\"function\",\"name\":\"authorizeMinter\",\"constant\":false,\"payable\":false,\"inputs\":[{\"type\":\"address\",\"name\":\"_minter\"}],\"outputs\":[]},{\"type\":\"function\",\"name\":\"authorizedMinters\",\"constant\":true,\"stateMutability\":\"view\",\"payable\":false,\"inputs\":[{\"type\":\"address\",\"name\":\"\"}],\"outputs\":[{\"type\":\"bool\",\"name\":\"\"}]},{\"type\":\"function\",\"name\":\"balanceOf\",\"constant\":true,\"stateMutability\":\"view\",\"payable\":false,\"inputs\":[{\"type\":\"address\",\"name\":\"account\"}],\"outputs\":[{\"type\":\"uint256\",\"name\":\"\"}]},{\"type\":\"function\",\"name\":\"claimAnnualReward\",\"constant\":false,\"payable\":false,\"inputs\":[],\"outputs\":[]},{\"type\":\"function\",\"name\":\"decimals\",\"constant\":true,\"stateMutability\":\"view\",\"payable\":false,\"inputs\":[],\"outputs\":[{\"type\":\"uint8\",\"name\":\"\"}]},{\"type\":\"function\",\"name\":\"donorRewards\",\"constant\":true,\"stateMutability\":\"view\",\"payable\":false,\"inputs\":[{\"type\":\"address\",\"name\":\"\"}],\"outputs\":[{\"type\":\"uint256\",\"name\":\"\"}]},{\"type\":\"function\",\"name\":\"getTimeUntilNextReward\",\"constant\":true,\"stateMutability\":\"view\",\"payable\":false,\"inputs\":[{\"type\":\"address\",\"name\":\"_donor\"}],\"outputs\":[{\"type\":\"uint256\",\"name\":\"\"}]},{\"type\":\"function\",\"name\":\"getTotalRewards\",\"constant\":true,\"stateMutability\":\"view\",\"payable\":false,\"inputs\":[{\"type\":\"address\",\"name\":\"_donor\"}],\"outputs\":[{\"type\":\"uint256\",\"name\":\"\"}]},{\"type\":\"function\",\"name\":\"lastRewardTime\",\"constant\":true,\"stateMutability\":\"view\",\"payable\":false,\"inputs\":[{\"type\":\"address\",\"name\":\"\"}],\"outputs\":[{\"type\":\"uint256\",\"name\":\"\"}]},{\"type\":\"function\",\"name\":\"name\",\"constant\":true,\"stateMutability\":\"view\",\"payable\":false,\"inputs\":[],\"outputs\":[{\"type\":\"string\",\"name\":\"\"}]},{\"type\":\"function\",\"name\":\"owner\",\"constant\":true,\"stateMutability\":\"view\",\"payable\":false,\"inputs\":[],\"outputs\":[{\"type\":\"address\",\"name\":\"\"}]},{\"type\":\"function\",\"name\":\"renounceOwnership\",\"constant\":false,\"payable\":false,\"inputs\":[],\"outputs\":[]},{\"type\":\"function\",\"name\":\"revokeMinter\",\"constant\":false,\"payable\":false,\"inputs\":[{\"type\":\"address\",\"name\":\"_minter\"}],\"outputs\":[]},{\"type\":\"function\",\"name\":\"rewardDonation\",\"constant\":false,\"payable\":false,\"inputs\":[{\"type\":\"address\",\"name\":\"_donor\"}],\"outputs\":[]},{\"type\":\"function\",\"name\":\"rewardDonorRegistration\",\"constant\":false,\"payable\":false,\"inputs\":[{\"type\":\"address\",\"name\":\"_donor\"}],\"outputs\":[]},{\"type\":\"function\",\"name\":\"symbol\",\"constant\":true,\"stateMutability\":\"view\",\"payable\":false,\"inputs\":[],\"outputs\":[{\"type\":\"string\",\"name\":\"\"}]},{\"type\":\"function\",\"name\":\"totalSupply\",\"constant\":true,\"stateMutability\":\"view\",\"payable\":false,\"inputs\":[],\"outputs\":[{\"type\":\"uint256\",\"name\":\"\"}]},{\"type\":\"function\",\"name\":\"transfer\",\"constant\":false,\"payable\":false,\"inputs\":[{\"type\":\"address\",\"name\":\"to\"},{\"type\":\"uint256\",\"name\":\"value\"}],\"outputs\":[{\"type\":\"bool\",\"name\":\"\"}]},{\"type\":\"function\",\"name\":\"transferFrom\",\"constant\":false,\"payable\":false,\"inputs\":[{\"type\":\"address\",\"name\":\"from\"},{\"type\":\"address\",\"name\":\"to\"},{\"type\":\"uint256\",\"name\":\"value\"}],\"outputs\":[{\"type\":\"bool\",\"name\":\"\"}]},{\"type\":\"function\",\"name\":\"transferOwnership\",\"constant\":false,\"payable\":false,\"inputs\":[{\"type\":\"address\",\"name\":\"newOwner\"}],\"outputs\":[]}]",
    "ChainOfCustody": "[{\"type\":\"event\",\"anonymous\":false,\"name\":\"CustodyEventLogged\",\"inputs\":[{\"type\":\"uint256\",\"name\":\"organId\",\"indexed\":true},{\"type\":\"uint256\",\"name\":\"eventId\",\"indexed\":true},{\"type\":\"uint8\",\"name\":\"eventType\",\"indexed\":false},{\"type\":\"address\",\"name\":\"handler\",\"indexed\":true},{\"type\":\"string\",\"name\":\"location\",\"indexed\":false}]},{\"type\":\"event\",\"anonymous\":false,\"name\":\"EventVerified\",\"inputs\":[{\"type\":\"uint256\",\"name\":\"organId\",\"indexed\":true},{\"type\":\"uint256\",\"name\":\"eventId\",\"indexed\":true}]},{\"type\":\"function\",\"name\":\"emergencyStop\",\"constant\":false,\"payable\":false,\"inputs\":[{\"type\":\"uint256\",\"name\":\"_organId\"},{\"type\":\"string\",\"name\":\"_reason\"}],\"outputs\":[]},{\"type\":\"function\",\"name\":\"eventCounter\",\"constant\":true,\"stateMutability\":\"view\",\"payable\":false,\"inputs\":[{\"type\":\"uint256\",\"name\":\"\"}],\"outputs\":[{\"type\":\"uint256\",\"name\":\"\"}]},{\"type\":\"function\",\"name\":\"getCustodyChain\",\"constant\":true,\"stateMutability\":\"view\",\"payable\":false,\"inputs\":[{\"type\":\"uint256\",\"name\":\"_organId\"}],\"outputs\":[{\"type\":\"tuple[]\",\"name\":\"\",\"components\":[{\"type\":\"uint256\",\"name\":\"eventId\"},{\"type\":\"uint256\",\"name\":\"organId\"},{\"type\":\"uint8\",\"name\":\"eventType\"},{\"type\":\"address\",\"name\":\"handler\"},{\"type\":\"string\",\"name\":\"location\"},{\"type\":\"uint256\",\"name\":\"timestamp\"},{\"type\":\"string\",\"name\":\"notes\"},{\"type\":\"string\",\"name\":\"documentCID\"},{\"type\":\"bool\",\"name\":\"verified\"}]}]},{\"type\":\"function\",\"name\":\"getEventCount\",\"constant\":true,\"stateMutability\":\"view\",\"payable\":false,\"inputs\":[{\"type\":\"uint256\",\"name\":\"_organId\"}],\"outputs\":[{\"type\":\"uint256\",\"name\":\"\"}]},{\"type\":\"function\",\"name\":\"getLatestEvent\",\"constant\":true,\"stateMutability\":\"view\",\"payable\":false,\"inputs\":[{\"type\":\"uint256\",\"name\":\"_organId\"}],\"outputs\":[{\"type\":\"tuple\",\"name\":\"\",\"components\":[{\"type\":\"uint256\",\"name\":\"eventId\"},{\"type\":\"uint256\",\"name\":\"organId\"},{\"type\":\"uint8\",\"name\":\"eventType\"},{\"type\":\"address\",\"name\":\"handler\"},{\"type\":\"string\",\"name\":\"location\"},{\"type\":\"uint256\",\"name\":\"timestamp\"},{\"type\":\"string\",\"name\":\"notes\"},{\"type\":\"string\",\"name\":\"documentCID\"},{\"type\":\"bool\",\"name\":\"verified\"}]}]},{\"type\":\"function\",\"name\":\"logCustodyEvent\",\"constant\":false,\"payable\":false,\"inputs\":[{\"type\":\"uint256\",\"name\":\"_organId\"},{\"type\":\"uint8\",\"name\":\"_eventType\"},{\"type\":\"string\",\"name\":\"_location\"},{\"type\":\"string\",\"name\":\"_notes\"},{\"type\":\"string\",\"name\":\"_documentCID\"}],\"outputs\":[{\"type\":\"uint256\",\"name\":\"\"}]},{\"type\":\"function\",\"name\":\"organCustodyChain\",\"constant\":true,\"stateMutability\":\"view\",\"payable\":false,\"inputs\":[{\"type\":\"uint256\",\"name\":\"\"},{\"type\":\"uint256\",\"name\":\"\"}],\"outputs\":[{\"type\":\"uint256\",\"name\":\"eventId\"},{\"type\":\"uint256\",\"name\":\"organId\"},{\"type\":\"uint8\",\"name\":\"eventType\"},{\"type\":\"address\",\"name\":\"handler\"},{\"type\":\"string\",\"name\":\"location\"},{\"type\":\"uint256\",\"name\":\"timestamp\"},{\"type\":\"string\",\"name\":\"notes\"},{\"type\":\"string\",\"name\":\"documentCID\"},{\"type\":\"bool\",\"name\":\"verified\"}]},{\"type\":\"function\",\"name\":\"verifyEvent\",\"constant\":false,\"payable\":false,\"inputs\":[{\"type\":\"uint256\",\"name\":\"_organId\"},{\"type\":\"uint256\",\"name\":\"_eventId\"}],\"outputs\":[]}]"
  },
  "networkInfo": {
    "name": "localhost",
    "chainId": 31337,
    "rpcUrl": "http://127.0.0.1:8545"
  },
  "deployedAt": "2025-06-15T05:21:20.940Z"
}